dova_ladekast_fetcher-0.0.2.data/data/my_data/data_file
sample/__init__.py
sample/package_data.dat
sample/simple.py
dova_ladekast_fetcher-0.0.2.dist-info/LICENSE.txt
dova_ladekast_fetcher-0.0.2.dist-info/METADATA
dova_ladekast_fetcher-0.0.2.dist-info/WHEEL
dova_ladekast_fetcher-0.0.2.dist-info/entry_points.txt
dova_ladekast_fetcher-0.0.2.dist-info/top_level.txt
dova_ladekast_fetcher-0.0.2.dist-info/RECORD
