Metadata-Version: 2.1
Name: dova-ladekast-fetcher
Version: 0.0.2
Summary: Python class to talk to DOVA ladekast REST API
Home-page: https://github.com/pypa/dova-ladekast-fetcher
Author: Daniel Overdevest
Author-email: d.overdevest@pzh.nl
License: UNKNOWN
Project-URL: Bug Reports, https://https://github.com/Provincie-Zuid-Holland/dova-ladekast-fetcher/issues
Project-URL: Source, https://github.com/Provincie-Zuid-Holland/dova-ladekast-fetcher
Keywords: dova,ladekast
Platform: UNKNOWN
Classifier: Development Status :: 4 - Beta
Classifier: Intended Audience :: Developers
Classifier: Topic :: Software Development :: Build Tools
Classifier: License :: OSI Approved :: MIT License
Classifier: Programming Language :: Python :: 3
Classifier: Programming Language :: Python :: 3.5
Classifier: Programming Language :: Python :: 3.6
Classifier: Programming Language :: Python :: 3.7
Classifier: Programming Language :: Python :: 3.8
Classifier: Programming Language :: Python :: 3 :: Only
Requires-Python: >=3.5, <4
License-File: LICENSE.txt
Requires-Dist: requests (>=2.25.0)
Provides-Extra: dev
Requires-Dist: check-manifest ; extra == 'dev'
Requires-Dist: python-dotenv (>=0.15.0) ; extra == 'dev'
Provides-Extra: test
Requires-Dist: coverage ; extra == 'test'
